artd/__init__.py
artd/asgi.py
artd/settings.py
artd/urls.py
artd/wsgi.py
artd_openpay/__init__.py
artd_openpay/admin.py
artd_openpay/apps.py
artd_openpay/models.py
artd_openpay/tests.py
artd_openpay/views.py
artd_openpay/migrations/0001_initial.py
artd_openpay/migrations/0002_rename_partner_openpay_partner.py
artd_openpay/migrations/0003_alter_openpay_options_openpaycard.py
artd_openpay/migrations/0004_alter_openpaycard_other_data.py
artd_openpay/migrations/0005_openpaycharge.py
artd_openpay/migrations/0006_alter_openpaycharge_charge_id.py
artd_openpay/migrations/__init__.py
artd_openpay/utils/__init__.py
artd_openpay/utils/openpay.py
artd_openpay-0.0.1.dist-info/LICENSE
artd_openpay-0.0.1.dist-info/METADATA
artd_openpay-0.0.1.dist-info/WHEEL
artd_openpay-0.0.1.dist-info/top_level.txt
artd_openpay-0.0.1.dist-info/RECORD
